README.md
setup.cfg
setup.py
gauss_binom_test/Binomialdistribution.py
gauss_binom_test/Gaussiandistribution.py
gauss_binom_test/Generaldistribution.py
gauss_binom_test/__init__.py
gauss_binom_test.egg-info/PKG-INFO
gauss_binom_test.egg-info/SOURCES.txt
gauss_binom_test.egg-info/dependency_links.txt
gauss_binom_test.egg-info/not-zip-safe
gauss_binom_test.egg-info/top_level.txt