Metadata-Version: 2.1
Name: gauss-binom-test
Version: 0.2.3
Summary: Gaussian and Binomial distributions
Home-page: UNKNOWN
Author: ludovico
License: MIT
Platform: UNKNOWN
Classifier: Programming Language :: Python :: 3
Classifier: License :: OSI Approved :: MIT License
Classifier: Operating System :: OS Independent
Requires-Python: >=3.6
